bmcs_utils/__init__.py
bmcs_utils/api.py
bmcs_utils/app_window.py
bmcs_utils/app_window_example.py
bmcs_utils/config.py
bmcs_utils/controller.py
bmcs_utils/i_model.py
bmcs_utils/item.py
bmcs_utils/model.py
bmcs_utils/model_dict.py
bmcs_utils/model_list.py
bmcs_utils/model_notify_mixin.py
bmcs_utils/model_tree_node_mixin.py
bmcs_utils/mpl_utils.py
bmcs_utils/parametric_study.py
bmcs_utils/plot_backend.py
bmcs_utils/plot_backend_k3d.py
bmcs_utils/plot_backend_mpl.py
bmcs_utils/symb_expr.py
bmcs_utils/symb_expr_quad_example.py
bmcs_utils/tree_node.py
bmcs_utils/version.py
bmcs_utils/view.py
bmcs_utils/data_cache/__init__.py
bmcs_utils/data_cache/data_cache.py
bmcs_utils/demo/__init__.py
bmcs_utils/demo/app_window.py
bmcs_utils/demo/layout_model.py
bmcs_utils/demo/model_with_history_slider.py
bmcs_utils/demo/model_with_progress_bar.py
bmcs_utils/demo/model_with_volume.py
bmcs_utils/demo/shape_model.py
bmcs_utils/editors/__init__.py
bmcs_utils/editors/dict_editor.py
bmcs_utils/editors/editor_factory.py
bmcs_utils/editors/editors.py
bmcs_utils/editors/either_type_editor.py
bmcs_utils/editors/enum_type_editor.py
bmcs_utils/editors/float_range_slider_editor.py
bmcs_utils/editors/history_editor.py
bmcs_utils/editors/instance_editor.py
bmcs_utils/editors/list_editor.py
bmcs_utils/editors/progress_editor.py
bmcs_utils/k3d_utils/__init__.py
bmcs_utils/k3d_utils/extrusion_for_3d_curve.py
bmcs_utils/k3d_utils/k3d_utils.py
bmcs_utils/misc/__init__.py
bmcs_utils/misc/plot_tools.py
bmcs_utils/symbol/__init__.py
bmcs_utils/symbol/cymbol.py
bmcs_utils/trait_types/__init__.py
bmcs_utils/trait_types/dict_type.py
bmcs_utils/trait_types/either_type.py
bmcs_utils/trait_types/either_type2.py
bmcs_utils/trait_types/enum_type.py
bmcs_utils/trait_types/instance_type.py
bmcs_utils/trait_types/list_type.py
bmcs_utils/trait_types/selector_type.py
bmcs_utils/trait_types/trait_types.py
bmcs_utils/trait_types/weakref_type.py
bmcs_utils-0.0.38a0.dist-info/METADATA
bmcs_utils-0.0.38a0.dist-info/WHEEL
bmcs_utils-0.0.38a0.dist-info/top_level.txt
bmcs_utils-0.0.38a0.dist-info/RECORD
