Metadata-Version: 2.1
Name: bmcs_utils
Version: 0.0.38a0
Summary: Suite of utilities for to implementation of bmcs_utils for brittle-matrix composites.
Home-page: https://github.com/bmcs-group/bmcs_utils
Author: BMCS-Group
Author-email: rostislav.chudoba@rwt-aachen.de
License: MIT
Classifier: License :: OSI Approved :: MIT License
Classifier: Programming Language :: Python
Classifier: Programming Language :: Python :: 3
Classifier: Programming Language :: Python :: 3.6
Classifier: Programming Language :: Python :: Implementation :: CPython
Classifier: Programming Language :: Python :: Implementation :: PyPy
Requires-Python: >=3.6.0
